prompts_mcp/__init__.py
prompts_mcp/main.py
prompts_mcp-1.6.0.dist-info/WHEEL
prompts_mcp-1.6.0.dist-info/entry_points.txt
prompts_mcp-1.6.0.dist-info/METADATA
prompts_mcp-1.6.0.dist-info/RECORD
