Metadata-Version: 2.3
Name: prompts-mcp
Version: 1.6.0
Summary: Model Context Protocol (MCP) server of Markdown based prompts.
Keywords: model-context-protocol,mcp,prompts,ai,llm
Author: Anssi Syrjäsalo
Author-email: Anssi Syrjäsalo <ai@alkue.com>
License: LGPLv3
Classifier: License :: OSI Approved :: GNU Lesser General Public License v3 (LGPLv3)
Classifier: Operating System :: OS Independent
Classifier: Programming Language :: Python :: 3.10
Classifier: Programming Language :: Python :: 3.11
Classifier: Programming Language :: Python :: 3.12
Classifier: Programming Language :: Python :: 3.13
Requires-Dist: mcp>=1.14.1
Requires-Python: >=3.10
Project-URL: Documentation, https://github.com/alkue-com/prompts-mcp/blob/main/README.md
Project-URL: Homepage, https://pypi.org/project/prompts-mcp
Project-URL: Repository, https://github.com/alkue-com/prompts-mcp
